initvenv/__init__.py
initvenv/_launcher.py
initvenv/scripts/initvenv.bat
initvenv/scripts/initvenv.exe
initvenv-0.2.1.dist-info/licenses/LICENSE
initvenv-0.2.1.dist-info/METADATA
initvenv-0.2.1.dist-info/WHEEL
initvenv-0.2.1.dist-info/entry_points.txt
initvenv-0.2.1.dist-info/top_level.txt
initvenv-0.2.1.dist-info/RECORD
