Metadata-Version: 2.4
Name: initvenv
Version: 0.2.1
Summary: Cross-language CLI tool written in C# to initialize Python virtual environments instantly with one command: 'initvenv'.
Author-email: Dev2Forge <support@dev2forge.software>
Maintainer-email: tutosrive <tutosriveorg@gmail.com>
License-Expression: GPL-3.0
Project-URL: Homepage, https://www.dev2forge.software/initvenv/
Project-URL: Repository, https://github.com/Dev2Forge/initvenv
Project-URL: Issues, https://github.com/Dev2Forge/initvenv/issues
Project-URL: Download, https://sourceforge.net/projects/Init-Venv/
Project-URL: Source, https://github.com/Dev2Forge/Init-Venv
Keywords: initvenv,auto-venv,instant-setup,zero-config,python-bootstrap,one-command,venv-creator,dev-automation,fast-python-start,project-starter
Classifier: Development Status :: 4 - Beta
Classifier: Intended Audience :: Developers
Classifier: Topic :: Software Development :: Build Tools
Classifier: Topic :: Utilities
Classifier: Topic :: System :: Installation/Setup
Classifier: Programming Language :: C#
Classifier: Programming Language :: Python :: 3
Classifier: Environment :: Console
Classifier: Operating System :: Microsoft :: Windows
Classifier: Operating System :: POSIX :: Linux
Classifier: Operating System :: MacOS :: MacOS X
Requires-Python: >=3.7
License-File: LICENSE
Dynamic: license-file
